odoo/addons/crm_security_group/README.rst
odoo/addons/crm_security_group/__init__.py
odoo/addons/crm_security_group/__manifest__.py
odoo/addons/crm_security_group/i18n/crm_security_group.pot
odoo/addons/crm_security_group/i18n/es.po
odoo/addons/crm_security_group/i18n/it.po
odoo/addons/crm_security_group/i18n/pt_BR.po
odoo/addons/crm_security_group/migrations/18.0.1.1.0/noupdate_changes.xml
odoo/addons/crm_security_group/migrations/18.0.1.1.0/post-migration.py
odoo/addons/crm_security_group/readme/CONTRIBUTORS.md
odoo/addons/crm_security_group/readme/DESCRIPTION.md
odoo/addons/crm_security_group/readme/ROADMAP.md
odoo/addons/crm_security_group/security/ir.model.access.csv
odoo/addons/crm_security_group/security/security.xml
odoo/addons/crm_security_group/static/description/icon.png
odoo/addons/crm_security_group/static/description/index.html
odoo/addons/crm_security_group/tests/__init__.py
odoo/addons/crm_security_group/tests/test_crm_security.py
odoo/addons/crm_security_group/views/crm_lead_views.xml
odoo/addons/crm_security_group/views/crm_team_views.xml
odoo/addons/crm_security_group/views/menu_items.xml
odoo_addon_crm_security_group-18.0.1.2.0.3.dist-info/METADATA
odoo_addon_crm_security_group-18.0.1.2.0.3.dist-info/WHEEL
odoo_addon_crm_security_group-18.0.1.2.0.3.dist-info/top_level.txt
odoo_addon_crm_security_group-18.0.1.2.0.3.dist-info/RECORD
