Metadata-Version: 2.1
Name: odoo-addon-crm_security_group
Version: 18.0.1.2.0.3
Requires-Python: >=3.10
Requires-Dist: odoo==18.0.*
Summary: Add new group in Sales to show only CRM
Home-page: https://github.com/OCA/crm
License: AGPL-3
Author: Tecnativa, Odoo Community Association (OCA)
Author-email: support@odoo-community.org
Classifier: Programming Language :: Python
Classifier: Framework :: Odoo
Classifier: Framework :: Odoo :: 18.0
Classifier: License :: OSI Approved :: GNU Affero General Public License v3
